hypia/__init__.py
hypia/functionals.py
hypia/transforms.py
hypia-0.0.3.dist-info/LICENSE
hypia-0.0.3.dist-info/METADATA
hypia-0.0.3.dist-info/WHEEL
hypia-0.0.3.dist-info/top_level.txt
hypia-0.0.3.dist-info/RECORD
