Metadata-Version: 2.1
Name: hypia
Version: 0.0.3
Summary: A package for doing hyper-spectral image augmentation for deep learning.
Home-page: https://github.com/rhero12/Hypia
Author: John Armstrong
Author-email: j.armstrong.2@research.gla.ac.uk
License: UNKNOWN
Platform: UNKNOWN
Classifier: Programming Language :: Python :: 3
Classifier: License :: OSI Approved :: MIT License
Classifier: Operating System :: OS Independent
